u_boot_pylib/README.rst
u_boot_pylib/__init__.py
u_boot_pylib/__main__.py
u_boot_pylib/command.py
u_boot_pylib/cros_subprocess.py
u_boot_pylib/gitutil.py
u_boot_pylib/terminal.py
u_boot_pylib/test_util.py
u_boot_pylib/tools.py
u_boot_pylib/tout.py
u_boot_pylib-0.0.7.dist-info/licenses/LICENSE
u_boot_pylib-0.0.7.dist-info/METADATA
u_boot_pylib-0.0.7.dist-info/WHEEL
u_boot_pylib-0.0.7.dist-info/top_level.txt
u_boot_pylib-0.0.7.dist-info/RECORD
